LAB4/circuits/LAB4-02/src/bcd_to_binary.v
`timescale 1ns/1ps
// 출처: Glaysia/ece2_474 v1.1.0 docs/FPGA_additional.md (2. BCD를 이진수로 변환)
// 십의 자리와 일의 자리를 각각 0~9로 입력합니다.
module bcd_to_binary(
    input wire [3:0] ten, one,
    output wire [6:0] binary,
    output wire valid
);
    assign binary = ten * 7'd10 + one;
    assign valid = (ten <= 9) && (one <= 9);
endmodule

LAB4/circuits/LAB4-02/src/bcd_conv.v
`timescale 1ns/1ps
// 출처: Glaysia/ece2_474 v1.1.0 docs/FPGA_additional.md (2. BCD를 이진수로 변환)
module bcd_conv(
    input wire [3:0] one, ten,
    output wire [6:0] bin,
    output wire valid
);
    bcd_to_binary u_convert(ten, one, bin, valid);
endmodule

LAB4/circuits/LAB4-02/sim/tb.sv
`timescale 1ns/1ps
// 출처: Glaysia/ece2_474 v1.1.0 docs/FPGA_additional.md (2. BCD 변환 테스트벤치)
// 추가: 보고서 파형용 wave.vcd 저장 (initial 블록 하나)
module tb;
    reg [3:0] ten, one;
    wire [6:0] bin;
    wire valid;
    bcd_conv dut(one, ten, bin, valid);
    integer t, o;
    initial begin $dumpfile("wave.vcd"); $dumpvars(0, tb); end
    initial begin
        for(t=0;t<16;t=t+1)
            for(o=0;o<16;o=o+1) begin
                ten=t; one=o; #1;
                if(valid !== ((t<10)&&(o<10))) $fatal(1,"BCD valid");
                if(t<10 && o<10 && bin !== t*10+o) $fatal(1,"BCD value");
            end
        $display("PASS BCD: 100 valid and 156 invalid inputs"); $finish;
    end
    initial begin #1000; $fatal(1,"timeout"); end
endmodule

LAB4/circuits/LAB4-02/results/icarus_wave.vcd
$date
	Wed Oct 07 16:21:17 2026
$end
$version
	Icarus Verilog
$end
$timescale
	1ps
$end
$scope module tb $end
$var wire 1 ! valid $end
$var wire 7 " bin [6:0] $end
$var reg 4 # one [3:0] $end
$var reg 4 $ ten [3:0] $end
$var integer 32 % o [31:0] $end
$var integer 32 & t [31:0] $end
$scope module dut $end
$var wire 4 ' one [3:0] $end
$var wire 4 ( ten [3:0] $end
$var wire 1 ! valid $end
$var wire 7 ) bin [6:0] $end
$scope module u_convert $end
$var wire 4 * one [3:0] $end
$var wire 4 + ten [3:0] $end
$var wire 1 ! valid $end
$var wire 7 , binary [6:0] $end
$upscope $end
$upscope $end
$upscope $end
$enddefinitions $end
$comment Show the parameter values. $end
$dumpall
$end
#0
$dumpvars
b0 ,
b0 +
b0 *
b0 )
b0 (
b0 '
b0 &
b0 %
b0 $
b0 #
b0 "
1!
$end
#1000
b1 "
b1 )
b1 ,
b1 #
b1 '
b1 *
b1 %
#2000
b10 "
b10 )
b10 ,
b10 #
b10 '
b10 *
b10 %
#3000
b11 "
b11 )
b11 ,
b11 #
b11 '
b11 *
b11 %
#4000
b100 "
b100 )
b100 ,
b100 #
b100 '
b100 *
b100 %
#5000
b101 "
b101 )
b101 ,
b101 #
b101 '
b101 *
b101 %
#6000
b110 "
b110 )
b110 ,
b110 #
b110 '
b110 *
b110 %
#7000
b111 "
b111 )
b111 ,
b111 #
b111 '
b111 *
b111 %
#8000
b1000 "
b1000 )
b1000 ,
b1000 #
b1000 '
b1000 *
b1000 %
#9000
b1001 "
b1001 )
b1001 ,
b1001 #
b1001 '
b1001 *
b1001 %
#10000
0!
b1010 "
b1010 )
b1010 ,
b1010 #
b1010 '
b1010 *
b1010 %
#11000
b1011 "
b1011 )
b1011 ,
b1011 #
b1011 '
b1011 *
b1011 %
#12000
b1100 "
b1100 )
b1100 ,
b1100 #
b1100 '
b1100 *
b1100 %
#13000
b1101 "
b1101 )
b1101 ,
b1101 #
b1101 '
b1101 *
b1101 %
#14000
b1110 "
b1110 )
b1110 ,
b1110 #
b1110 '
b1110 *
b1110 %
#15000
b1111 "
b1111 )
b1111 ,
b1111 #
b1111 '
b1111 *
b1111 %
#16000
1!
b0 #
b0 '
b0 *
b1010 "
b1010 )
b1010 ,
b1 $
b1 (
b1 +
b1 &
b0 %
#17000
b1011 "
b1011 )
b1011 ,
b1 #
b1 '
b1 *
b1 %
#18000
b1100 "
b1100 )
b1100 ,
b10 #
b10 '
b10 *
b10 %
#19000
b1101 "
b1101 )
b1101 ,
b11 #
b11 '
b11 *
b11 %
#20000
b1110 "
b1110 )
b1110 ,
b100 #
b100 '
b100 *
b100 %
#21000
b1111 "
b1111 )
b1111 ,
b101 #
b101 '
b101 *
b101 %
#22000
b10000 "
b10000 )
b10000 ,
b110 #
b110 '
b110 *
b110 %
#23000
b10001 "
b10001 )
b10001 ,
b111 #
b111 '
b111 *
b111 %
#24000
b10010 "
b10010 )
b10010 ,
b1000 #
b1000 '
b1000 *
b1000 %
#25000
b10011 "
b10011 )
b10011 ,
b1001 #
b1001 '
b1001 *
b1001 %
#26000
0!
b10100 "
b10100 )
b10100 ,
b1010 #
b1010 '
b1010 *
b1010 %
#27000
b10101 "
b10101 )
b10101 ,
b1011 #
b1011 '
b1011 *
b1011 %
#28000
b10110 "
b10110 )
b10110 ,
b1100 #
b1100 '
b1100 *
b1100 %
#29000
b10111 "
b10111 )
b10111 ,
b1101 #
b1101 '
b1101 *
b1101 %
#30000
b11000 "
b11000 )
b11000 ,
b1110 #
b1110 '
b1110 *
b1110 %
#31000
b11001 "
b11001 )
b11001 ,
b1111 #
b1111 '
b1111 *
b1111 %
#32000
1!
b0 #
b0 '
b0 *
b10100 "
b10100 )
b10100 ,
b10 $
b10 (
b10 +
b10 &
b0 %
#33000
b10101 "
b10101 )
b10101 ,
b1 #
b1 '
b1 *
b1 %
#34000
b10110 "
b10110 )
b10110 ,
b10 #
b10 '
b10 *
b10 %
#35000
b10111 "
b10111 )
b10111 ,
b11 #
b11 '
b11 *
b11 %
#36000
b11000 "
b11000 )
b11000 ,
b100 #
b100 '
b100 *
b100 %
#37000
b11001 "
b11001 )
b11001 ,
b101 #
b101 '
b101 *
b101 %
#38000
b11010 "
b11010 )
b11010 ,
b110 #
b110 '
b110 *
b110 %
#39000
b11011 "
b11011 )
b11011 ,
b111 #
b111 '
b111 *
b111 %
#40000
b11100 "
b11100 )
b11100 ,
b1000 #
b1000 '
b1000 *
b1000 %
#41000
b11101 "
b11101 )
b11101 ,
b1001 #
b1001 '
b1001 *
b1001 %
#42000
0!
b11110 "
b11110 )
b11110 ,
b1010 #
b1010 '
b1010 *
b1010 %
#43000
b11111 "
b11111 )
b11111 ,
b1011 #
b1011 '
b1011 *
b1011 %
#44000
b100000 "
b100000 )
b100000 ,
b1100 #
b1100 '
b1100 *
b1100 %
#45000
b100001 "
b100001 )
b100001 ,
b1101 #
b1101 '
b1101 *
b1101 %
#46000
b100010 "
b100010 )
b100010 ,
b1110 #
b1110 '
b1110 *
b1110 %
#47000
b100011 "
b100011 )
b100011 ,
b1111 #
b1111 '
b1111 *
b1111 %
#48000
1!
b0 #
b0 '
b0 *
b11110 "
b11110 )
b11110 ,
b11 $
b11 (
b11 +
b11 &
b0 %
#49000
b11111 "
b11111 )
b11111 ,
b1 #
b1 '
b1 *
b1 %
#50000
b100000 "
b100000 )
b100000 ,
b10 #
b10 '
b10 *
b10 %
#51000
b100001 "
b100001 )
b100001 ,
b11 #
b11 '
b11 *
b11 %
#52000
b100010 "
b100010 )
b100010 ,
b100 #
b100 '
b100 *
b100 %
#53000
b100011 "
b100011 )
b100011 ,
b101 #
b101 '
b101 *
b101 %
#54000
b100100 "
b100100 )
b100100 ,
b110 #
b110 '
b110 *
b110 %
#55000
b100101 "
b100101 )
b100101 ,
b111 #
b111 '
b111 *
b111 %
#56000
b100110 "
b100110 )
b100110 ,
b1000 #
b1000 '
b1000 *
b1000 %
#57000
b100111 "
b100111 )
b100111 ,
b1001 #
b1001 '
b1001 *
b1001 %
#58000
0!
b101000 "
b101000 )
b101000 ,
b1010 #
b1010 '
b1010 *
b1010 %
#59000
b101001 "
b101001 )
b101001 ,
b1011 #
b1011 '
b1011 *
b1011 %
#60000
b101010 "
b101010 )
b101010 ,
b1100 #
b1100 '
b1100 *
b1100 %
#61000
b101011 "
b101011 )
b101011 ,
b1101 #
b1101 '
b1101 *
b1101 %
#62000
b101100 "
b101100 )
b101100 ,
b1110 #
b1110 '
b1110 *
b1110 %
#63000
b101101 "
b101101 )
b101101 ,
b1111 #
b1111 '
b1111 *
b1111 %
#64000
1!
b0 #
b0 '
b0 *
b101000 "
b101000 )
b101000 ,
b100 $
b100 (
b100 +
b100 &
b0 %
#65000
b101001 "
b101001 )
b101001 ,
b1 #
b1 '
b1 *
b1 %
#66000
b101010 "
b101010 )
b101010 ,
b10 #
b10 '
b10 *
b10 %
#67000
b101011 "
b101011 )
b101011 ,
b11 #
b11 '
b11 *
b11 %
#68000
b101100 "
b101100 )
b101100 ,
b100 #
b100 '
b100 *
b100 %
#69000
b101101 "
b101101 )
b101101 ,
b101 #
b101 '
b101 *
b101 %
#70000
b101110 "
b101110 )
b101110 ,
b110 #
b110 '
b110 *
b110 %
#71000
b101111 "
b101111 )
b101111 ,
b111 #
b111 '
b111 *
b111 %
#72000
b110000 "
b110000 )
b110000 ,
b1000 #
b1000 '
b1000 *
b1000 %
#73000
b110001 "
b110001 )
b110001 ,
b1001 #
b1001 '
b1001 *
b1001 %
#74000
0!
b110010 "
b110010 )
b110010 ,
b1010 #
b1010 '
b1010 *
b1010 %
#75000
b110011 "
b110011 )
b110011 ,
b1011 #
b1011 '
b1011 *
b1011 %
#76000
b110100 "
b110100 )
b110100 ,
b1100 #
b1100 '
b1100 *
b1100 %
#77000
b110101 "
b110101 )
b110101 ,
b1101 #
b1101 '
b1101 *
b1101 %
#78000
b110110 "
b110110 )
b110110 ,
b1110 #
b1110 '
b1110 *
b1110 %
#79000
b110111 "
b110111 )
b110111 ,
b1111 #
b1111 '
b1111 *
b1111 %
#80000
1!
b0 #
b0 '
b0 *
b110010 "
b110010 )
b110010 ,
b101 $
b101 (
b101 +
b101 &
b0 %
#81000
b110011 "
b110011 )
b110011 ,
b1 #
b1 '
b1 *
b1 %
#82000
b110100 "
b110100 )
b110100 ,
b10 #
b10 '
b10 *
b10 %
#83000
b110101 "
b110101 )
b110101 ,
b11 #
b11 '
b11 *
b11 %
#84000
b110110 "
b110110 )
b110110 ,
b100 #
b100 '
b100 *
b100 %
#85000
b110111 "
b110111 )
b110111 ,
b101 #
b101 '
b101 *
b101 %
#86000
b111000 "
b111000 )
b111000 ,
b110 #
b110 '
b110 *
b110 %
#87000
b111001 "
b111001 )
b111001 ,
b111 #
b111 '
b111 *
b111 %
#88000
b111010 "
b111010 )
b111010 ,
b1000 #
b1000 '
b1000 *
b1000 %
#89000
b111011 "
b111011 )
b111011 ,
b1001 #
b1001 '
b1001 *
b1001 %
#90000
0!
b111100 "
b111100 )
b111100 ,
b1010 #
b1010 '
b1010 *
b1010 %
#91000
b111101 "
b111101 )
b111101 ,
b1011 #
b1011 '
b1011 *
b1011 %
#92000
b111110 "
b111110 )
b111110 ,
b1100 #
b1100 '
b1100 *
b1100 %
#93000
b111111 "
b111111 )
b111111 ,
b1101 #
b1101 '
b1101 *
b1101 %
#94000
b1000000 "
b1000000 )
b1000000 ,
b1110 #
b1110 '
b1110 *
b1110 %
#95000
b1000001 "
b1000001 )
b1000001 ,
b1111 #
b1111 '
b1111 *
b1111 %
#96000
1!
b0 #
b0 '
b0 *
b111100 "
b111100 )
b111100 ,
b110 $
b110 (
b110 +
b110 &
b0 %
#97000
b111101 "
b111101 )
b111101 ,
b1 #
b1 '
b1 *
b1 %
#98000
b111110 "
b111110 )
b111110 ,
b10 #
b10 '
b10 *
b10 %
#99000
b111111 "
b111111 )
b111111 ,
b11 #
b11 '
b11 *
b11 %
#100000
b1000000 "
b1000000 )
b1000000 ,
b100 #
b100 '
b100 *
b100 %
#101000
b1000001 "
b1000001 )
b1000001 ,
b101 #
b101 '
b101 *
b101 %
#102000
b1000010 "
b1000010 )
b1000010 ,
b110 #
b110 '
b110 *
b110 %
#103000
b1000011 "
b1000011 )
b1000011 ,
b111 #
b111 '
b111 *
b111 %
#104000
b1000100 "
b1000100 )
b1000100 ,
b1000 #
b1000 '
b1000 *
b1000 %
#105000
b1000101 "
b1000101 )
b1000101 ,
b1001 #
b1001 '
b1001 *
b1001 %
#106000
0!
b1000110 "
b1000110 )
b1000110 ,
b1010 #
b1010 '
b1010 *
b1010 %
#107000
b1000111 "
b1000111 )
b1000111 ,
b1011 #
b1011 '
b1011 *
b1011 %
#108000
b1001000 "
b1001000 )
b1001000 ,
b1100 #
b1100 '
b1100 *
b1100 %
#109000
b1001001 "
b1001001 )
b1001001 ,
b1101 #
b1101 '
b1101 *
b1101 %
#110000
b1001010 "
b1001010 )
b1001010 ,
b1110 #
b1110 '
b1110 *
b1110 %
#111000
b1001011 "
b1001011 )
b1001011 ,
b1111 #
b1111 '
b1111 *
b1111 %
#112000
1!
b0 #
b0 '
b0 *
b1000110 "
b1000110 )
b1000110 ,
b111 $
b111 (
b111 +
b111 &
b0 %
#113000
b1000111 "
b1000111 )
b1000111 ,
b1 #
b1 '
b1 *
b1 %
#114000
b1001000 "
b1001000 )
b1001000 ,
b10 #
b10 '
b10 *
b10 %
#115000
b1001001 "
b1001001 )
b1001001 ,
b11 #
b11 '
b11 *
b11 %
#116000
b1001010 "
b1001010 )
b1001010 ,
b100 #
b100 '
b100 *
b100 %
#117000
b1001011 "
b1001011 )
b1001011 ,
b101 #
b101 '
b101 *
b101 %
#118000
b1001100 "
b1001100 )
b1001100 ,
b110 #
b110 '
b110 *
b110 %
#119000
b1001101 "
b1001101 )
b1001101 ,
b111 #
b111 '
b111 *
b111 %
#120000
b1001110 "
b1001110 )
b1001110 ,
b1000 #
b1000 '
b1000 *
b1000 %
#121000
b1001111 "
b1001111 )
b1001111 ,
b1001 #
b1001 '
b1001 *
b1001 %
#122000
0!
b1010000 "
b1010000 )
b1010000 ,
b1010 #
b1010 '
b1010 *
b1010 %
#123000
b1010001 "
b1010001 )
b1010001 ,
b1011 #
b1011 '
b1011 *
b1011 %
#124000
b1010010 "
b1010010 )
b1010010 ,
b1100 #
b1100 '
b1100 *
b1100 %
#125000
b1010011 "
b1010011 )
b1010011 ,
b1101 #
b1101 '
b1101 *
b1101 %
#126000
b1010100 "
b1010100 )
b1010100 ,
b1110 #
b1110 '
b1110 *
b1110 %
#127000
b1010101 "
b1010101 )
b1010101 ,
b1111 #
b1111 '
b1111 *
b1111 %
#128000
1!
b0 #
b0 '
b0 *
b1010000 "
b1010000 )
b1010000 ,
b1000 $
b1000 (
b1000 +
b1000 &
b0 %
#129000
b1010001 "
b1010001 )
b1010001 ,
b1 #
b1 '
b1 *
b1 %
#130000
b1010010 "
b1010010 )
b1010010 ,
b10 #
b10 '
b10 *
b10 %
#131000
b1010011 "
b1010011 )
b1010011 ,
b11 #
b11 '
b11 *
b11 %
#132000
b1010100 "
b1010100 )
b1010100 ,
b100 #
b100 '
b100 *
b100 %
#133000
b1010101 "
b1010101 )
b1010101 ,
b101 #
b101 '
b101 *
b101 %
#134000
b1010110 "
b1010110 )
b1010110 ,
b110 #
b110 '
b110 *
b110 %
#135000
b1010111 "
b1010111 )
b1010111 ,
b111 #
b111 '
b111 *
b111 %
#136000
b1011000 "
b1011000 )
b1011000 ,
b1000 #
b1000 '
b1000 *
b1000 %
#137000
b1011001 "
b1011001 )
b1011001 ,
b1001 #
b1001 '
b1001 *
b1001 %
#138000
0!
b1011010 "
b1011010 )
b1011010 ,
b1010 #
b1010 '
b1010 *
b1010 %
#139000
b1011011 "
b1011011 )
b1011011 ,
b1011 #
b1011 '
b1011 *
b1011 %
#140000
b1011100 "
b1011100 )
b1011100 ,
b1100 #
b1100 '
b1100 *
b1100 %
#141000
b1011101 "
b1011101 )
b1011101 ,
b1101 #
b1101 '
b1101 *
b1101 %
#142000
b1011110 "
b1011110 )
b1011110 ,
b1110 #
b1110 '
b1110 *
b1110 %
#143000
b1011111 "
b1011111 )
b1011111 ,
b1111 #
b1111 '
b1111 *
b1111 %
#144000
1!
b0 #
b0 '
b0 *
b1011010 "
b1011010 )
b1011010 ,
b1001 $
b1001 (
b1001 +
b1001 &
b0 %
#145000
b1011011 "
b1011011 )
b1011011 ,
b1 #
b1 '
b1 *
b1 %
#146000
b1011100 "
b1011100 )
b1011100 ,
b10 #
b10 '
b10 *
b10 %
#147000
b1011101 "
b1011101 )
b1011101 ,
b11 #
b11 '
b11 *
b11 %
#148000
b1011110 "
b1011110 )
b1011110 ,
b100 #
b100 '
b100 *
b100 %
#149000
b1011111 "
b1011111 )
b1011111 ,
b101 #
b101 '
b101 *
b101 %
#150000
b1100000 "
b1100000 )
b1100000 ,
b110 #
b110 '
b110 *
b110 %
#151000
b1100001 "
b1100001 )
b1100001 ,
b111 #
b111 '
b111 *
b111 %
#152000
b1100010 "
b1100010 )
b1100010 ,
b1000 #
b1000 '
b1000 *
b1000 %
#153000
b1100011 "
b1100011 )
b1100011 ,
b1001 #
b1001 '
b1001 *
b1001 %
#154000
0!
b1100100 "
b1100100 )
b1100100 ,
b1010 #
b1010 '
b1010 *
b1010 %
#155000
b1100101 "
b1100101 )
b1100101 ,
b1011 #
b1011 '
b1011 *
b1011 %
#156000
b1100110 "
b1100110 )
b1100110 ,
b1100 #
b1100 '
b1100 *
b1100 %
#157000
b1100111 "
b1100111 )
b1100111 ,
b1101 #
b1101 '
b1101 *
b1101 %
#158000
b1101000 "
b1101000 )
b1101000 ,
b1110 #
b1110 '
b1110 *
b1110 %
#159000
b1101001 "
b1101001 )
b1101001 ,
b1111 #
b1111 '
b1111 *
b1111 %
#160000
b0 #
b0 '
b0 *
b1100100 "
b1100100 )
b1100100 ,
b1010 $
b1010 (
b1010 +
b1010 &
b0 %
#161000
b1100101 "
b1100101 )
b1100101 ,
b1 #
b1 '
b1 *
b1 %
#162000
b1100110 "
b1100110 )
b1100110 ,
b10 #
b10 '
b10 *
b10 %
#163000
b1100111 "
b1100111 )
b1100111 ,
b11 #
b11 '
b11 *
b11 %
#164000
b1101000 "
b1101000 )
b1101000 ,
b100 #
b100 '
b100 *
b100 %
#165000
b1101001 "
b1101001 )
b1101001 ,
b101 #
b101 '
b101 *
b101 %
#166000
b1101010 "
b1101010 )
b1101010 ,
b110 #
b110 '
b110 *
b110 %
#167000
b1101011 "
b1101011 )
b1101011 ,
b111 #
b111 '
b111 *
b111 %
#168000
b1101100 "
b1101100 )
b1101100 ,
b1000 #
b1000 '
b1000 *
b1000 %
#169000
b1101101 "
b1101101 )
b1101101 ,
b1001 #
b1001 '
b1001 *
b1001 %
#170000
b1101110 "
b1101110 )
b1101110 ,
b1010 #
b1010 '
b1010 *
b1010 %
#171000
b1101111 "
b1101111 )
b1101111 ,
b1011 #
b1011 '
b1011 *
b1011 %
#172000
b1110000 "
b1110000 )
b1110000 ,
b1100 #
b1100 '
b1100 *
b1100 %
#173000
b1110001 "
b1110001 )
b1110001 ,
b1101 #
b1101 '
b1101 *
b1101 %
#174000
b1110010 "
b1110010 )
b1110010 ,
b1110 #
b1110 '
b1110 *
b1110 %
#175000
b1110011 "
b1110011 )
b1110011 ,
b1111 #
b1111 '
b1111 *
b1111 %
#176000
b0 #
b0 '
b0 *
b1101110 "
b1101110 )
b1101110 ,
b1011 $
b1011 (
b1011 +
b1011 &
b0 %
#177000
b1101111 "
b1101111 )
b1101111 ,
b1 #
b1 '
b1 *
b1 %
#178000
b1110000 "
b1110000 )
b1110000 ,
b10 #
b10 '
b10 *
b10 %
#179000
b1110001 "
b1110001 )
b1110001 ,
b11 #
b11 '
b11 *
b11 %
#180000
b1110010 "
b1110010 )
b1110010 ,
b100 #
b100 '
b100 *
b100 %
#181000
b1110011 "
b1110011 )
b1110011 ,
b101 #
b101 '
b101 *
b101 %
#182000
b1110100 "
b1110100 )
b1110100 ,
b110 #
b110 '
b110 *
b110 %
#183000
b1110101 "
b1110101 )
b1110101 ,
b111 #
b111 '
b111 *
b111 %
#184000
b1110110 "
b1110110 )
b1110110 ,
b1000 #
b1000 '
b1000 *
b1000 %
#185000
b1110111 "
b1110111 )
b1110111 ,
b1001 #
b1001 '
b1001 *
b1001 %
#186000
b1111000 "
b1111000 )
b1111000 ,
b1010 #
b1010 '
b1010 *
b1010 %
#187000
b1111001 "
b1111001 )
b1111001 ,
b1011 #
b1011 '
b1011 *
b1011 %
#188000
b1111010 "
b1111010 )
b1111010 ,
b1100 #
b1100 '
b1100 *
b1100 %
#189000
b1111011 "
b1111011 )
b1111011 ,
b1101 #
b1101 '
b1101 *
b1101 %
#190000
b1111100 "
b1111100 )
b1111100 ,
b1110 #
b1110 '
b1110 *
b1110 %
#191000
b1111101 "
b1111101 )
b1111101 ,
b1111 #
b1111 '
b1111 *
b1111 %
#192000
b0 #
b0 '
b0 *
b1111000 "
b1111000 )
b1111000 ,
b1100 $
b1100 (
b1100 +
b1100 &
b0 %
#193000
b1111001 "
b1111001 )
b1111001 ,
b1 #
b1 '
b1 *
b1 %
#194000
b1111010 "
b1111010 )
b1111010 ,
b10 #
b10 '
b10 *
b10 %
#195000
b1111011 "
b1111011 )
b1111011 ,
b11 #
b11 '
b11 *
b11 %
#196000
b1111100 "
b1111100 )
b1111100 ,
b100 #
b100 '
b100 *
b100 %
#197000
b1111101 "
b1111101 )
b1111101 ,
b101 #
b101 '
b101 *
b101 %
#198000
b1111110 "
b1111110 )
b1111110 ,
b110 #
b110 '
b110 *
b110 %
#199000
b1111111 "
b1111111 )
b1111111 ,
b111 #
b111 '
b111 *
b111 %
#200000
b0 "
b0 )
b0 ,
b1000 #
b1000 '
b1000 *
b1000 %
#201000
b1 "
b1 )
b1 ,
b1001 #
b1001 '
b1001 *
b1001 %
#202000
b10 "
b10 )
b10 ,
b1010 #
b1010 '
b1010 *
b1010 %
#203000
b11 "
b11 )
b11 ,
b1011 #
b1011 '
b1011 *
b1011 %
#204000
b100 "
b100 )
b100 ,
b1100 #
b1100 '
b1100 *
b1100 %
#205000
b101 "
b101 )
b101 ,
b1101 #
b1101 '
b1101 *
b1101 %
#206000
b110 "
b110 )
b110 ,
b1110 #
b1110 '
b1110 *
b1110 %
#207000
b111 "
b111 )
b111 ,
b1111 #
b1111 '
b1111 *
b1111 %
#208000
b0 #
b0 '
b0 *
b10 "
b10 )
b10 ,
b1101 $
b1101 (
b1101 +
b1101 &
b0 %
#209000
b11 "
b11 )
b11 ,
b1 #
b1 '
b1 *
b1 %
#210000
b100 "
b100 )
b100 ,
b10 #
b10 '
b10 *
b10 %
#211000
b101 "
b101 )
b101 ,
b11 #
b11 '
b11 *
b11 %
#212000
b110 "
b110 )
b110 ,
b100 #
b100 '
b100 *
b100 %
#213000
b111 "
b111 )
b111 ,
b101 #
b101 '
b101 *
b101 %
#214000
b1000 "
b1000 )
b1000 ,
b110 #
b110 '
b110 *
b110 %
#215000
b1001 "
b1001 )
b1001 ,
b111 #
b111 '
b111 *
b111 %
#216000
b1010 "
b1010 )
b1010 ,
b1000 #
b1000 '
b1000 *
b1000 %
#217000
b1011 "
b1011 )
b1011 ,
b1001 #
b1001 '
b1001 *
b1001 %
#218000
b1100 "
b1100 )
b1100 ,
b1010 #
b1010 '
b1010 *
b1010 %
#219000
b1101 "
b1101 )
b1101 ,
b1011 #
b1011 '
b1011 *
b1011 %
#220000
b1110 "
b1110 )
b1110 ,
b1100 #
b1100 '
b1100 *
b1100 %
#221000
b1111 "
b1111 )
b1111 ,
b1101 #
b1101 '
b1101 *
b1101 %
#222000
b10000 "
b10000 )
b10000 ,
b1110 #
b1110 '
b1110 *
b1110 %
#223000
b10001 "
b10001 )
b10001 ,
b1111 #
b1111 '
b1111 *
b1111 %
#224000
b0 #
b0 '
b0 *
b1100 "
b1100 )
b1100 ,
b1110 $
b1110 (
b1110 +
b1110 &
b0 %
#225000
b1101 "
b1101 )
b1101 ,
b1 #
b1 '
b1 *
b1 %
#226000
b1110 "
b1110 )
b1110 ,
b10 #
b10 '
b10 *
b10 %
#227000
b1111 "
b1111 )
b1111 ,
b11 #
b11 '
b11 *
b11 %
#228000
b10000 "
b10000 )
b10000 ,
b100 #
b100 '
b100 *
b100 %
#229000
b10001 "
b10001 )
b10001 ,
b101 #
b101 '
b101 *
b101 %
#230000
b10010 "
b10010 )
b10010 ,
b110 #
b110 '
b110 *
b110 %
#231000
b10011 "
b10011 )
b10011 ,
b111 #
b111 '
b111 *
b111 %
#232000
b10100 "
b10100 )
b10100 ,
b1000 #
b1000 '
b1000 *
b1000 %
#233000
b10101 "
b10101 )
b10101 ,
b1001 #
b1001 '
b1001 *
b1001 %
#234000
b10110 "
b10110 )
b10110 ,
b1010 #
b1010 '
b1010 *
b1010 %
#235000
b10111 "
b10111 )
b10111 ,
b1011 #
b1011 '
b1011 *
b1011 %
#236000
b11000 "
b11000 )
b11000 ,
b1100 #
b1100 '
b1100 *
b1100 %
#237000
b11001 "
b11001 )
b11001 ,
b1101 #
b1101 '
b1101 *
b1101 %
#238000
b11010 "
b11010 )
b11010 ,
b1110 #
b1110 '
b1110 *
b1110 %
#239000
b11011 "
b11011 )
b11011 ,
b1111 #
b1111 '
b1111 *
b1111 %
#240000
b0 #
b0 '
b0 *
b10110 "
b10110 )
b10110 ,
b1111 $
b1111 (
b1111 +
b1111 &
b0 %
#241000
b10111 "
b10111 )
b10111 ,
b1 #
b1 '
b1 *
b1 %
#242000
b11000 "
b11000 )
b11000 ,
b10 #
b10 '
b10 *
b10 %
#243000
b11001 "
b11001 )
b11001 ,
b11 #
b11 '
b11 *
b11 %
#244000
b11010 "
b11010 )
b11010 ,
b100 #
b100 '
b100 *
b100 %
#245000
b11011 "
b11011 )
b11011 ,
b101 #
b101 '
b101 *
b101 %
#246000
b11100 "
b11100 )
b11100 ,
b110 #
b110 '
b110 *
b110 %
#247000
b11101 "
b11101 )
b11101 ,
b111 #
b111 '
b111 *
b111 %
#248000
b11110 "
b11110 )
b11110 ,
b1000 #
b1000 '
b1000 *
b1000 %
#249000
b11111 "
b11111 )
b11111 ,
b1001 #
b1001 '
b1001 *
b1001 %
#250000
b100000 "
b100000 )
b100000 ,
b1010 #
b1010 '
b1010 *
b1010 %
#251000
b100001 "
b100001 )
b100001 ,
b1011 #
b1011 '
b1011 *
b1011 %
#252000
b100010 "
b100010 )
b100010 ,
b1100 #
b1100 '
b1100 *
b1100 %
#253000
b100011 "
b100011 )
b100011 ,
b1101 #
b1101 '
b1101 *
b1101 %
#254000
b100100 "
b100100 )
b100100 ,
b1110 #
b1110 '
b1110 *
b1110 %
#255000
b100101 "
b100101 )
b100101 ,
b1111 #
b1111 '
b1111 *
b1111 %
#256000
b10000 &
b10000 %
